{"aggregation_lineage":null,"baseline":{"eligible_year_values":[2016,2017,2018,2019,2020,2021,2022,2023],"eligible_years":8,"end_year":2023,"excluded_years":[2014,2015],"slots":[{"count":8,"max":2170585,"mean":2016459.5,"median":2004130.5,"min":1855715,"q1":1988349.75,"q3":2052710,"slot":1},{"count":8,"max":1986217,"mean":1844546.375,"median":1840861.5,"min":1667466,"q1":1792055.25,"q3":1896821,"slot":2},{"count":8,"max":2193242,"mean":2029519.625,"median":2022386.5,"min":1909347,"q1":1982046,"q3":2059893.75,"slot":3},{"count":8,"max":2130159,"mean":1891336.625,"median":1885853.5,"min":1441838,"q1":1868043.25,"q3":1992869.5,"slot":4},{"count":8,"max":2184490,"mean":1918643,"median":1954102.5,"min":1293812,"q1":1923951.75,"q3":2014775.5,"slot":5},{"count":8,"max":2076725,"mean":1882863.625,"median":1899302,"min":1511750,"q1":1853223.75,"q3":1957577.75,"slot":6},{"count":8,"max":2171718,"mean":1978399.25,"median":1977246,"min":1660936,"q1":1954494.25,"q3":2039141.75,"slot":7},{"count":8,"max":2161552,"mean":2007702.875,"median":1984784.5,"min":1809090,"q1":1972714,"q3":2055184.5,"slot":8},{"count":8,"max":2115914,"mean":1952136.875,"median":1932234,"min":1809978,"q1":1916555.75,"q3":1972501,"slot":9},{"count":8,"max":2169916,"mean":2027985.625,"median":2005835,"min":1856795,"q1":1987036,"q3":2080489,"slot":10},{"count":8,"max":2136827,"mean":1969808.375,"median":1947517.5,"min":1827390,"q1":1926664.75,"q3":1999674,"slot":11},{"count":8,"max":2237407,"mean":2029178.375,"median":2002897.5,"min":1888815,"q1":1979335,"q3":2066485.5,"slot":12}],"start_year":2014,"status":"ok"},"dimensions":{"coordinate":"1.4.1","vector":"v107757048"},"distribution":{"changes":{"count":123,"excess_kurtosis":4.035292455382802,"fit":{"aic":3234.379857853209,"best_candidate":"Normal","criterion":"AIC (single stdlib baseline candidate)","diagnostics":{"jarque_bera_statistic":98.82669309260721,"log_likelihood":-1615.1899289266046,"p_value":null,"parameters":{"mean":903.260162601626,"standard_deviation":122111.14153796398}},"reason":"Normal candidate diagnostic only; not a definitive distribution classification.","status":"candidate_diagnostic","tested_candidates":["Normal"]},"histogram":[{"count":1,"lower":-611417.0,"upper":-555117.1875},{"count":0,"lower":-555117.1875,"upper":-498817.375},{"count":0,"lower":-498817.375,"upper":-442517.5625},{"count":0,"lower":-442517.5625,"upper":-386217.75},{"count":0,"lower":-386217.75,"upper":-329917.9375},{"count":1,"lower":-329917.9375,"upper":-273618.125},{"count":2,"lower":-273618.125,"upper":-217318.3125},{"count":6,"lower":-217318.3125,"upper":-161018.5},{"count":7,"lower":-161018.5,"upper":-104718.6875},{"count":23,"lower":-104718.6875,"upper":-48418.875},{"count":21,"lower":-48418.875,"upper":7880.9375},{"count":25,"lower":7880.9375,"upper":64180.75},{"count":23,"lower":64180.75,"upper":120480.5625},{"count":5,"lower":120480.5625,"upper":176780.375},{"count":5,"lower":176780.375,"upper":233080.1875},{"count":4,"lower":233080.1875,"upper":289380.0}],"iqr":143062.0,"max":289380.0,"mean":903.260162601626,"median":10198.0,"min":-611417.0,"period_end":"2026-04","period_start":"2016-01","q1":-70041.5,"q3":73020.5,"skewness":-0.865978058084044,"status":"ok","stddev":122610.57569406532},"levels":{"count":124,"excess_kurtosis":2.704540421811074,"fit":{"aic":3340.1031802277957,"best_candidate":"Normal","criterion":"AIC (single stdlib baseline candidate)","diagnostics":{"jarque_bera_statistic":58.03488585667864,"log_likelihood":-1668.0515901138979,"p_value":null,"parameters":{"mean":2016091.7177419355,"standard_deviation":168230.5130372705}},"reason":"Normal candidate diagnostic only; not a definitive distribution classification.","status":"candidate_diagnostic","tested_candidates":["Normal"]},"histogram":[{"count":1,"lower":1293812.0,"upper":1379728.0833333333},{"count":1,"lower":1379728.0833333333,"upper":1465644.1666666667},{"count":1,"lower":1465644.1666666667,"upper":1551560.25},{"count":0,"lower":1551560.25,"upper":1637476.3333333333},{"count":2,"lower":1637476.3333333333,"upper":1723392.4166666665},{"count":3,"lower":1723392.4166666665,"upper":1809308.5},{"count":14,"lower":1809308.5,"upper":1895224.5833333333},{"count":31,"lower":1895224.5833333333,"upper":1981140.6666666665},{"count":23,"lower":1981140.6666666665,"upper":2067056.75},{"count":19,"lower":2067056.75,"upper":2152972.833333333},{"count":19,"lower":2152972.833333333,"upper":2238888.9166666665},{"count":10,"lower":2238888.9166666665,"upper":2324805.0}],"iqr":214954.5,"max":2324805.0,"mean":2016091.7177419355,"median":1993842.5,"min":1293812.0,"period_end":"2026-04","period_start":"2016-01","q1":1926664.75,"q3":2141619.25,"skewness":-0.9896994063471395,"status":"ok","stddev":168912.9925659068}},"frequency":"monthly","freshness":{"expected_next_release_at":null,"expected_period":null,"last_success_at":"2026-07-20T19:20:43.789785+00:00","latest_numeric_period":"2026-04","latest_observation_status":"observed","latest_period":"2026-04","retrieved_at":"2026-07-20T19:20:43.789785+00:00","source_release_at":null,"source_updated_at":null,"status":"unknown"},"generated_at":"2026-07-20T19:20:43.789785+00:00","geography_id":"ca","history":[{"period":"2016-01","slot":1,"status":"observed","value":2041220,"year":2016},{"period":"2016-02","slot":2,"status":"observed","value":1868985,"year":2016},{"period":"2016-03","slot":3,"status":"observed","value":1969503,"year":2016},{"period":"2016-04","slot":4,"status":"observed","value":1873385,"year":2016},{"period":"2016-05","slot":5,"status":"observed","value":1921710,"year":2016},{"period":"2016-06","slot":6,"status":"observed","value":1905924,"year":2016},{"period":"2016-07","slot":7,"status":"observed","value":1969281,"year":2016},{"period":"2016-08","slot":8,"status":"observed","value":1972856,"year":2016},{"period":"2016-09","slot":9,"status":"observed","value":1931664,"year":2016},{"period":"2016-10","slot":10,"status":"observed","value":1983607,"year":2016},{"period":"2016-11","slot":11,"status":"observed","value":1952142,"year":2016},{"period":"2016-12","slot":12,"status":"observed","value":2017657,"year":2016},{"period":"2017-01","slot":1,"status":"observed","value":2013836,"year":2017},{"period":"2017-02","slot":2,"status":"observed","value":1838194,"year":2017},{"period":"2017-03","slot":3,"status":"observed","value":2051180,"year":2017},{"period":"2017-04","slot":4,"status":"observed","value":1959339,"year":2017},{"period":"2017-05","slot":5,"status":"observed","value":1963774,"year":2017},{"period":"2017-06","slot":6,"status":"observed","value":1919289,"year":2017},{"period":"2017-07","slot":7,"status":"observed","value":1985211,"year":2017},{"period":"2017-08","slot":8,"status":"observed","value":2022235,"year":2017},{"period":"2017-09","slot":9,"status":"observed","value":1920557,"year":2017},{"period":"2017-10","slot":10,"status":"observed","value":1988942,"year":2017},{"period":"2017-11","slot":11,"status":"observed","value":1925227,"year":2017},{"period":"2017-12","slot":12,"status":"observed","value":1975918,"year":2017},{"period":"2018-01","slot":1,"status":"observed","value":1976373,"year":2018},{"period":"2018-02","slot":2,"status":"observed","value":1798285,"year":2018},{"period":"2018-03","slot":3,"status":"observed","value":1986227,"year":2018},{"period":"2018-04","slot":4,"status":"observed","value":1868992,"year":2018},{"period":"2018-05","slot":5,"status":"observed","value":1944431,"year":2018},{"period":"2018-06","slot":6,"status":"observed","value":1892680,"year":2018},{"period":"2018-07","slot":7,"status":"observed","value":2005335,"year":2018},{"period":"2018-08","slot":8,"status":"observed","value":1994092,"year":2018},{"period":"2018-09","slot":9,"status":"observed","value":1944189,"year":2018},{"period":"2018-10","slot":10,"status":"observed","value":2022728,"year":2018},{"period":"2018-11","slot":11,"status":"observed","value":1942893,"year":2018},{"period":"2018-12","slot":12,"status":"observed","value":1988138,"year":2018},{"period":"2019-01","slot":1,"status":"observed","value":1994425,"year":2019},{"period":"2019-02","slot":2,"status":"observed","value":1773366,"year":2019},{"period":"2019-03","slot":3,"status":"observed","value":1993593,"year":2019},{"period":"2019-04","slot":4,"status":"observed","value":1898322,"year":2019},{"period":"2019-05","slot":5,"status":"observed","value":1971437,"year":2019},{"period":"2019-06","slot":6,"status":"observed","value":1819698,"year":2019},{"period":"2019-07","slot":7,"status":"observed","value":1932238,"year":2019},{"period":"2019-08","slot":8,"status":"observed","value":1975477,"year":2019},{"period":"2019-09","slot":9,"status":"observed","value":1932804,"year":2019},{"period":"2019-10","slot":10,"status":"observed","value":2054119,"year":2019},{"period":"2019-11","slot":11,"status":"observed","value":1975926,"year":2019},{"period":"2019-12","slot":12,"status":"observed","value":2060462,"year":2019},{"period":"2020-01","slot":1,"status":"observed","value":2087180,"year":2020},{"period":"2020-02","slot":2,"status":"observed","value":1980329,"year":2020},{"period":"2020-03","slot":3,"status":"observed","value":2053255,"year":2020},{"period":"2020-04","slot":4,"status":"observed","value":1441838,"year":2020},{"period":"2020-05","slot":5,"status":"observed","value":1293812,"year":2020},{"period":"2020-06","slot":6,"status":"observed","value":1511750,"year":2020},{"period":"2020-07","slot":7,"status":"observed","value":1660936,"year":2020},{"period":"2020-08","slot":8,"status":"observed","value":1809090,"year":2020},{"period":"2020-09","slot":9,"status":"observed","value":1809978,"year":2020},{"period":"2020-10","slot":10,"status":"observed","value":1856795,"year":2020},{"period":"2020-11","slot":11,"status":"observed","value":1827390,"year":2020},{"period":"2020-12","slot":12,"status":"observed","value":1888815,"year":2020},{"period":"2021-01","slot":1,"status":"observed","value":1855715,"year":2021},{"period":"2021-02","slot":2,"status":"observed","value":1667466,"year":2021},{"period":"2021-03","slot":3,"status":"observed","value":1909347,"year":2021},{"period":"2021-04","slot":4,"status":"observed","value":1865197,"year":2021},{"period":"2021-05","slot":5,"status":"observed","value":1924699,"year":2021},{"period":"2021-06","slot":6,"status":"observed","value":1864399,"year":2021},{"period":"2021-07","slot":7,"status":"observed","value":1961913,"year":2021},{"period":"2021-08","slot":8,"status":"observed","value":1972288,"year":2021},{"period":"2021-09","slot":9,"status":"observed","value":1904552,"year":2021},{"period":"2021-10","slot":10,"status":"observed","value":1988179,"year":2021},{"period":"2021-11","slot":11,"status":"observed","value":1927144,"year":2021},{"period":"2021-12","slot":12,"status":"observed","value":1980474,"year":2021},{"period":"2022-01","slot":1,"status":"observed","value":1992342,"year":2022},{"period":"2022-02","slot":2,"status":"observed","value":1843529,"year":2022},{"period":"2022-03","slot":3,"status":"observed","value":2079810,"year":2022},{"period":"2022-04","slot":4,"status":"observed","value":2093461,"year":2022},{"period":"2022-05","slot":5,"status":"observed","value":2144791,"year":2022},{"period":"2022-06","slot":6,"status":"observed","value":2072444,"year":2022},{"period":"2022-07","slot":7,"status":"observed","value":2140562,"year":2022},{"period":"2022-08","slot":8,"status":"observed","value":2161552,"year":2022},{"period":"2022-09","slot":9,"status":"observed","value":2115914,"year":2022},{"period":"2022-10","slot":10,"status":"observed","value":2159599,"year":2022},{"period":"2022-11","slot":11,"status":"observed","value":2070918,"year":2022},{"period":"2022-12","slot":12,"status":"observed","value":2084556,"year":2022},{"period":"2023-01","slot":1,"status":"observed","value":2170585,"year":2023},{"period":"2023-02","slot":2,"status":"observed","value":1986217,"year":2023},{"period":"2023-03","slot":3,"status":"observed","value":2193242,"year":2023},{"period":"2023-04","slot":4,"status":"observed","value":2130159,"year":2023},{"period":"2023-05","slot":5,"status":"observed","value":2184490,"year":2023},{"period":"2023-06","slot":6,"status":"observed","value":2076725,"year":2023},{"period":"2023-07","slot":7,"status":"observed","value":2171718,"year":2023},{"period":"2023-08","slot":8,"status":"observed","value":2154033,"year":2023},{"period":"2023-09","slot":9,"status":"observed","value":2057437,"year":2023},{"period":"2023-10","slot":10,"status":"observed","value":2169916,"year":2023},{"period":"2023-11","slot":11,"status":"observed","value":2136827,"year":2023},{"period":"2023-12","slot":12,"status":"observed","value":2237407,"year":2023},{"period":"2024-01","slot":1,"status":"observed","value":2199829,"year":2024},{"period":"2024-02","slot":2,"status":"observed","value":2120202,"year":2024},{"period":"2024-03","slot":3,"status":"observed","value":2269343,"year":2024},{"period":"2024-04","slot":4,"status":"observed","value":2179895,"year":2024},{"period":"2024-05","slot":5,"status":"observed","value":2269296,"year":2024},{"period":"2024-06","slot":6,"status":"observed","value":2180271,"year":2024},{"period":"2024-07","slot":7,"status":"observed","value":2226291,"year":2024},{"period":"2024-08","slot":8,"status":"observed","value":2251670,"year":2024},{"period":"2024-09","slot":9,"status":"observed","value":2102243,"year":2024},{"period":"2024-10","slot":10,"status":"observed","value":2227149,"year":2024},{"period":"2024-11","slot":11,"status":"observed","value":2137027,"year":2024},{"period":"2024-12","slot":12,"status":"observed","value":2204500,"year":2024},{"period":"2025-01","slot":1,"status":"observed","value":2285868,"year":2025},{"period":"2025-02","slot":2,"status":"observed","value":2008423,"year":2025},{"period":"2025-03","slot":3,"status":"observed","value":2297803,"year":2025},{"period":"2025-04","slot":4,"status":"observed","value":2223995,"year":2025},{"period":"2025-05","slot":5,"status":"observed","value":2182407,"year":2025},{"period":"2025-06","slot":6,"status":"observed","value":2116171,"year":2025},{"period":"2025-07","slot":7,"status":"observed","value":2219269,"year":2025},{"period":"2025-08","slot":8,"status":"observed","value":2158465,"year":2025},{"period":"2025-09","slot":9,"status":"observed","value":2125800,"year":2025},{"period":"2025-10","slot":10,"status":"observed","value":2245711,"year":2025},{"period":"2025-11","slot":11,"status":"observed","value":2255909,"year":2025},{"period":"2025-12","slot":12,"status":"observed","value":2278109,"year":2025},{"period":"2026-01","slot":1,"status":"observed","value":2295826,"year":2026},{"period":"2026-02","slot":2,"status":"observed","value":2068134,"year":2026},{"period":"2026-03","slot":3,"status":"observed","value":2324805,"year":2026},{"period":"2026-04","slot":4,"status":"observed","value":2152321,"year":2026}],"latest":{"absolute_change":-172484,"distance_from_seasonal_median":266467.5,"percent_change":-7.41928892960915,"period":"2026-04","previous_period":"2026-03","seasonal_median":1885853.5,"seasonal_percentile":100.0,"value":2152321,"year_ago_period":"2025-04","yoy_absolute_change":-71674,"yoy_percent_change":-3.2227590439726708},"latest_source":{"period":"2026-04","status":"observed","value":2152321},"methodology_version":"2026-07-20.1","recent_years":[{"points":[{"period":"2024-01","slot":1,"status":"observed","value":2199829},{"period":"2024-02","slot":2,"status":"observed","value":2120202},{"period":"2024-03","slot":3,"status":"observed","value":2269343},{"period":"2024-04","slot":4,"status":"observed","value":2179895},{"period":"2024-05","slot":5,"status":"observed","value":2269296},{"period":"2024-06","slot":6,"status":"observed","value":2180271},{"period":"2024-07","slot":7,"status":"observed","value":2226291},{"period":"2024-08","slot":8,"status":"observed","value":2251670},{"period":"2024-09","slot":9,"status":"observed","value":2102243},{"period":"2024-10","slot":10,"status":"observed","value":2227149},{"period":"2024-11","slot":11,"status":"observed","value":2137027},{"period":"2024-12","slot":12,"status":"observed","value":2204500}],"year":2024},{"points":[{"period":"2025-01","slot":1,"status":"observed","value":2285868},{"period":"2025-02","slot":2,"status":"observed","value":2008423},{"period":"2025-03","slot":3,"status":"observed","value":2297803},{"period":"2025-04","slot":4,"status":"observed","value":2223995},{"period":"2025-05","slot":5,"status":"observed","value":2182407},{"period":"2025-06","slot":6,"status":"observed","value":2116171},{"period":"2025-07","slot":7,"status":"observed","value":2219269},{"period":"2025-08","slot":8,"status":"observed","value":2158465},{"period":"2025-09","slot":9,"status":"observed","value":2125800},{"period":"2025-10","slot":10,"status":"observed","value":2245711},{"period":"2025-11","slot":11,"status":"observed","value":2255909},{"period":"2025-12","slot":12,"status":"observed","value":2278109}],"year":2025},{"points":[{"period":"2026-01","slot":1,"status":"observed","value":2295826},{"period":"2026-02","slot":2,"status":"observed","value":2068134},{"period":"2026-03","slot":3,"status":"observed","value":2324805},{"period":"2026-04","slot":4,"status":"observed","value":2152321}],"year":2026}],"schema_version":"1.0.0","series_id":"can.statcan.crude.production.heavy.monthly","source_checksum":"e77fa31079399db71080e7f645017aeb91234e4e73c2be431e499ce23b64c1ad","unit":"cubic_metres"}
