{"aggregation_residuals":{"alignment_keys":["horizon","target_period"],"calibration_window":{"end":"2026-01-16","start":"2024-01-26"},"centered_on":"published_calibrated_point","method":"rolling_origin_actual_minus_calibrated_point","minimum_aligned_samples_per_horizon":40,"sample_count":309,"samples":[{"horizon":1,"residual":4.2,"target_period":"2024-01-26"},{"horizon":1,"residual":-4.2,"target_period":"2024-02-02"},{"horizon":1,"residual":-36.6,"target_period":"2024-02-09"},{"horizon":1,"residual":59.6,"target_period":"2024-02-16"},{"horizon":1,"residual":3.8,"target_period":"2024-02-23"},{"horizon":1,"residual":-64.6,"target_period":"2024-03-01"},{"horizon":1,"residual":-52.2,"target_period":"2024-03-08"},{"horizon":1,"residual":13.8,"target_period":"2024-03-15"},{"horizon":1,"residual":-9.4,"target_period":"2024-03-22"},{"horizon":1,"residual":-80.8,"target_period":"2024-03-29"},{"horizon":1,"residual":-21.2,"target_period":"2024-04-05"},{"horizon":1,"residual":30.6,"target_period":"2024-04-12"},{"horizon":1,"residual":-24.2,"target_period":"2024-04-19"},{"horizon":1,"residual":-10.6,"target_period":"2024-04-26"},{"horizon":1,"residual":26.4,"target_period":"2024-05-03"},{"horizon":1,"residual":-70.4,"target_period":"2024-05-10"},{"horizon":1,"residual":2.6,"target_period":"2024-05-17"},{"horizon":1,"residual":-44.4,"target_period":"2024-05-24"},{"horizon":1,"residual":-49,"target_period":"2024-05-31"},{"horizon":1,"residual":75.6,"target_period":"2024-06-07"},{"horizon":1,"residual":33,"target_period":"2024-06-14"},{"horizon":1,"residual":-28.4,"target_period":"2024-06-21"},{"horizon":1,"residual":87.4,"target_period":"2024-06-28"},{"horizon":1,"residual":0.2,"target_period":"2024-07-05"},{"horizon":1,"residual":-18.6,"target_period":"2024-07-12"},{"horizon":1,"residual":68,"target_period":"2024-07-19"},{"horizon":1,"residual":-53.4,"target_period":"2024-07-26"},{"horizon":1,"residual":-21.8,"target_period":"2024-08-02"},{"horizon":1,"residual":-67.4,"target_period":"2024-08-09"},{"horizon":1,"residual":73.4,"target_period":"2024-08-16"},{"horizon":1,"residual":-18.6,"target_period":"2024-08-23"},{"horizon":1,"residual":129.2,"target_period":"2024-08-30"},{"horizon":1,"residual":37.2,"target_period":"2024-09-06"},{"horizon":1,"residual":32.6,"target_period":"2024-09-13"},{"horizon":1,"residual":54.6,"target_period":"2024-09-20"},{"horizon":1,"residual":-84,"target_period":"2024-09-27"},{"horizon":1,"residual":18.4,"target_period":"2024-10-04"},{"horizon":1,"residual":102.6,"target_period":"2024-10-11"},{"horizon":1,"residual":57,"target_period":"2024-10-18"},{"horizon":1,"residual":10.4,"target_period":"2024-10-25"},{"horizon":1,"residual":-35.4,"target_period":"2024-11-01"},{"horizon":1,"residual":-17.8,"target_period":"2024-11-08"},{"horizon":1,"residual":26.2,"target_period":"2024-11-15"},{"horizon":1,"residual":-88.6,"target_period":"2024-11-22"},{"horizon":1,"residual":154,"target_period":"2024-11-29"},{"horizon":1,"residual":-28.4,"target_period":"2024-12-06"},{"horizon":1,"residual":15.4,"target_period":"2024-12-13"},{"horizon":1,"residual":-66.8,"target_period":"2024-12-20"},{"horizon":1,"residual":-2,"target_period":"2024-12-27"},{"horizon":1,"residual":4.6,"target_period":"2025-01-03"},{"horizon":1,"residual":0.6,"target_period":"2025-01-10"},{"horizon":1,"residual":8.8,"target_period":"2025-01-17"},{"horizon":1,"residual":-76.6,"target_period":"2025-01-24"},{"horizon":1,"residual":-9,"target_period":"2025-01-31"},{"horizon":1,"residual":-116.6,"target_period":"2025-02-07"},{"horizon":1,"residual":-13.6,"target_period":"2025-02-14"},{"horizon":1,"residual":-97.6,"target_period":"2025-02-21"},{"horizon":1,"residual":-35.2,"target_period":"2025-02-28"},{"horizon":1,"residual":-66.2,"target_period":"2025-03-07"},{"horizon":1,"residual":-32.8,"target_period":"2025-03-14"},{"horizon":1,"residual":20,"target_period":"2025-03-21"},{"horizon":1,"residual":138.8,"target_period":"2025-03-28"},{"horizon":1,"residual":67.6,"target_period":"2025-04-04"},{"horizon":1,"residual":-51.4,"target_period":"2025-04-11"},{"horizon":1,"residual":0.4,"target_period":"2025-04-18"},{"horizon":1,"residual":-54,"target_period":"2025-04-25"},{"horizon":1,"residual":-47.6,"target_period":"2025-05-02"},{"horizon":1,"residual":56.6,"target_period":"2025-05-09"},{"horizon":1,"residual":9.4,"target_period":"2025-05-16"},{"horizon":1,"residual":-33.8,"target_period":"2025-05-23"},{"horizon":1,"residual":-16.2,"target_period":"2025-05-30"},{"horizon":1,"residual":10,"target_period":"2025-06-06"},{"horizon":1,"residual":-16.4,"target_period":"2025-06-13"},{"horizon":1,"residual":89,"target_period":"2025-06-20"},{"horizon":1,"residual":-36,"target_period":"2025-06-27"},{"horizon":1,"residual":28.4,"target_period":"2025-07-04"},{"horizon":1,"residual":8.4,"target_period":"2025-07-11"},{"horizon":1,"residual":65.4,"target_period":"2025-07-18"},{"horizon":1,"residual":-45.2,"target_period":"2025-07-25"},{"horizon":1,"residual":-93.6,"target_period":"2025-08-01"},{"horizon":1,"residual":51,"target_period":"2025-08-08"},{"horizon":1,"residual":14.6,"target_period":"2025-08-15"},{"horizon":1,"residual":-81.6,"target_period":"2025-08-22"},{"horizon":1,"residual":82.2,"target_period":"2025-08-29"},{"horizon":1,"residual":-0.2,"target_period":"2025-09-05"},{"horizon":1,"residual":-29.8,"target_period":"2025-09-12"},{"horizon":1,"residual":122.2,"target_period":"2025-09-19"},{"horizon":1,"residual":17,"target_period":"2025-09-26"},{"horizon":1,"residual":-22.6,"target_period":"2025-10-03"},{"horizon":1,"residual":-71.2,"target_period":"2025-10-10"},{"horizon":1,"residual":2.6,"target_period":"2025-10-17"},{"horizon":1,"residual":-87.4,"target_period":"2025-10-24"},{"horizon":1,"residual":-41,"target_period":"2025-10-31"},{"horizon":1,"residual":-70.4,"target_period":"2025-11-07"},{"horizon":1,"residual":80.4,"target_period":"2025-11-14"},{"horizon":1,"residual":85.8,"target_period":"2025-11-21"},{"horizon":1,"residual":-117,"target_period":"2025-11-28"},{"horizon":1,"residual":66.6,"target_period":"2025-12-05"},{"horizon":1,"residual":2.2,"target_period":"2025-12-12"},{"horizon":1,"residual":49.4,"target_period":"2025-12-19"},{"horizon":1,"residual":-13.4,"target_period":"2025-12-26"},{"horizon":1,"residual":147.8,"target_period":"2026-01-02"},{"horizon":1,"residual":52.4,"target_period":"2026-01-09"},{"horizon":1,"residual":107.2,"target_period":"2026-01-16"},{"horizon":2,"residual":-4,"target_period":"2024-02-02"},{"horizon":2,"residual":-36.4,"target_period":"2024-02-09"},{"horizon":2,"residual":59.8,"target_period":"2024-02-16"},{"horizon":2,"residual":4,"target_period":"2024-02-23"},{"horizon":2,"residual":-64.4,"target_period":"2024-03-01"},{"horizon":2,"residual":-52,"target_period":"2024-03-08"},{"horizon":2,"residual":14,"target_period":"2024-03-15"},{"horizon":2,"residual":-9.2,"target_period":"2024-03-22"},{"horizon":2,"residual":-80.6,"target_period":"2024-03-29"},{"horizon":2,"residual":-21,"target_period":"2024-04-05"},{"horizon":2,"residual":30.8,"target_period":"2024-04-12"},{"horizon":2,"residual":-24,"target_period":"2024-04-19"},{"horizon":2,"residual":-10.4,"target_period":"2024-04-26"},{"horizon":2,"residual":26.6,"target_period":"2024-05-03"},{"horizon":2,"residual":-70.2,"target_period":"2024-05-10"},{"horizon":2,"residual":2.8,"target_period":"2024-05-17"},{"horizon":2,"residual":-44.2,"target_period":"2024-05-24"},{"horizon":2,"residual":-48.8,"target_period":"2024-05-31"},{"horizon":2,"residual":75.8,"target_period":"2024-06-07"},{"horizon":2,"residual":33.2,"target_period":"2024-06-14"},{"horizon":2,"residual":-28.2,"target_period":"2024-06-21"},{"horizon":2,"residual":87.6,"target_period":"2024-06-28"},{"horizon":2,"residual":0.4,"target_period":"2024-07-05"},{"horizon":2,"residual":-18.4,"target_period":"2024-07-12"},{"horizon":2,"residual":68.2,"target_period":"2024-07-19"},{"horizon":2,"residual":-53.2,"target_period":"2024-07-26"},{"horizon":2,"residual":-21.6,"target_period":"2024-08-02"},{"horizon":2,"residual":-67.2,"target_period":"2024-08-09"},{"horizon":2,"residual":73.6,"target_period":"2024-08-16"},{"horizon":2,"residual":-18.4,"target_period":"2024-08-23"},{"horizon":2,"residual":129.4,"target_period":"2024-08-30"},{"horizon":2,"residual":37.4,"target_period":"2024-09-06"},{"horizon":2,"residual":32.8,"target_period":"2024-09-13"},{"horizon":2,"residual":54.8,"target_period":"2024-09-20"},{"horizon":2,"residual":-83.8,"target_period":"2024-09-27"},{"horizon":2,"residual":18.6,"target_period":"2024-10-04"},{"horizon":2,"residual":102.8,"target_period":"2024-10-11"},{"horizon":2,"residual":57.2,"target_period":"2024-10-18"},{"horizon":2,"residual":10.6,"target_period":"2024-10-25"},{"horizon":2,"residual":-35.2,"target_period":"2024-11-01"},{"horizon":2,"residual":-17.6,"target_period":"2024-11-08"},{"horizon":2,"residual":26.4,"target_period":"2024-11-15"},{"horizon":2,"residual":-88.4,"target_period":"2024-11-22"},{"horizon":2,"residual":154.2,"target_period":"2024-11-29"},{"horizon":2,"residual":-28.2,"target_period":"2024-12-06"},{"horizon":2,"residual":15.6,"target_period":"2024-12-13"},{"horizon":2,"residual":-66.6,"target_period":"2024-12-20"},{"horizon":2,"residual":-1.8,"target_period":"2024-12-27"},{"horizon":2,"residual":4.8,"target_period":"2025-01-03"},{"horizon":2,"residual":0.8,"target_period":"2025-01-10"},{"horizon":2,"residual":9,"target_period":"2025-01-17"},{"horizon":2,"residual":-76.4,"target_period":"2025-01-24"},{"horizon":2,"residual":-8.8,"target_period":"2025-01-31"},{"horizon":2,"residual":-116.4,"target_period":"2025-02-07"},{"horizon":2,"residual":-13.4,"target_period":"2025-02-14"},{"horizon":2,"residual":-97.4,"target_period":"2025-02-21"},{"horizon":2,"residual":-35,"target_period":"2025-02-28"},{"horizon":2,"residual":-66,"target_period":"2025-03-07"},{"horizon":2,"residual":-32.6,"target_period":"2025-03-14"},{"horizon":2,"residual":20.2,"target_period":"2025-03-21"},{"horizon":2,"residual":139,"target_period":"2025-03-28"},{"horizon":2,"residual":67.8,"target_period":"2025-04-04"},{"horizon":2,"residual":-51.2,"target_period":"2025-04-11"},{"horizon":2,"residual":0.6,"target_period":"2025-04-18"},{"horizon":2,"residual":-53.8,"target_period":"2025-04-25"},{"horizon":2,"residual":-47.4,"target_period":"2025-05-02"},{"horizon":2,"residual":56.8,"target_period":"2025-05-09"},{"horizon":2,"residual":9.6,"target_period":"2025-05-16"},{"horizon":2,"residual":-33.6,"target_period":"2025-05-23"},{"horizon":2,"residual":-16,"target_period":"2025-05-30"},{"horizon":2,"residual":10.2,"target_period":"2025-06-06"},{"horizon":2,"residual":-16.2,"target_period":"2025-06-13"},{"horizon":2,"residual":89.2,"target_period":"2025-06-20"},{"horizon":2,"residual":-35.8,"target_period":"2025-06-27"},{"horizon":2,"residual":28.6,"target_period":"2025-07-04"},{"horizon":2,"residual":8.6,"target_period":"2025-07-11"},{"horizon":2,"residual":65.6,"target_period":"2025-07-18"},{"horizon":2,"residual":-45,"target_period":"2025-07-25"},{"horizon":2,"residual":-93.4,"target_period":"2025-08-01"},{"horizon":2,"residual":51.2,"target_period":"2025-08-08"},{"horizon":2,"residual":14.8,"target_period":"2025-08-15"},{"horizon":2,"residual":-81.4,"target_period":"2025-08-22"},{"horizon":2,"residual":82.4,"target_period":"2025-08-29"},{"horizon":2,"residual":0,"target_period":"2025-09-05"},{"horizon":2,"residual":-29.6,"target_period":"2025-09-12"},{"horizon":2,"residual":122.4,"target_period":"2025-09-19"},{"horizon":2,"residual":17.2,"target_period":"2025-09-26"},{"horizon":2,"residual":-22.4,"target_period":"2025-10-03"},{"horizon":2,"residual":-71,"target_period":"2025-10-10"},{"horizon":2,"residual":2.8,"target_period":"2025-10-17"},{"horizon":2,"residual":-87.2,"target_period":"2025-10-24"},{"horizon":2,"residual":-40.8,"target_period":"2025-10-31"},{"horizon":2,"residual":-70.2,"target_period":"2025-11-07"},{"horizon":2,"residual":80.6,"target_period":"2025-11-14"},{"horizon":2,"residual":86,"target_period":"2025-11-21"},{"horizon":2,"residual":-116.8,"target_period":"2025-11-28"},{"horizon":2,"residual":66.8,"target_period":"2025-12-05"},{"horizon":2,"residual":2.4,"target_period":"2025-12-12"},{"horizon":2,"residual":49.6,"target_period":"2025-12-19"},{"horizon":2,"residual":-13.2,"target_period":"2025-12-26"},{"horizon":2,"residual":148,"target_period":"2026-01-02"},{"horizon":2,"residual":52.6,"target_period":"2026-01-09"},{"horizon":2,"residual":107.4,"target_period":"2026-01-16"},{"horizon":3,"residual":-36.6,"target_period":"2024-02-09"},{"horizon":3,"residual":59.6,"target_period":"2024-02-16"},{"horizon":3,"residual":3.8,"target_period":"2024-02-23"},{"horizon":3,"residual":-64.6,"target_period":"2024-03-01"},{"horizon":3,"residual":-52.2,"target_period":"2024-03-08"},{"horizon":3,"residual":13.8,"target_period":"2024-03-15"},{"horizon":3,"residual":-9.4,"target_period":"2024-03-22"},{"horizon":3,"residual":-80.8,"target_period":"2024-03-29"},{"horizon":3,"residual":-21.2,"target_period":"2024-04-05"},{"horizon":3,"residual":30.6,"target_period":"2024-04-12"},{"horizon":3,"residual":-24.2,"target_period":"2024-04-19"},{"horizon":3,"residual":-10.6,"target_period":"2024-04-26"},{"horizon":3,"residual":26.4,"target_period":"2024-05-03"},{"horizon":3,"residual":-70.4,"target_period":"2024-05-10"},{"horizon":3,"residual":2.6,"target_period":"2024-05-17"},{"horizon":3,"residual":-44.4,"target_period":"2024-05-24"},{"horizon":3,"residual":-49,"target_period":"2024-05-31"},{"horizon":3,"residual":75.6,"target_period":"2024-06-07"},{"horizon":3,"residual":33,"target_period":"2024-06-14"},{"horizon":3,"residual":-28.4,"target_period":"2024-06-21"},{"horizon":3,"residual":87.4,"target_period":"2024-06-28"},{"horizon":3,"residual":0.2,"target_period":"2024-07-05"},{"horizon":3,"residual":-18.6,"target_period":"2024-07-12"},{"horizon":3,"residual":68,"target_period":"2024-07-19"},{"horizon":3,"residual":-53.4,"target_period":"2024-07-26"},{"horizon":3,"residual":-21.8,"target_period":"2024-08-02"},{"horizon":3,"residual":-67.4,"target_period":"2024-08-09"},{"horizon":3,"residual":73.4,"target_period":"2024-08-16"},{"horizon":3,"residual":-18.6,"target_period":"2024-08-23"},{"horizon":3,"residual":129.2,"target_period":"2024-08-30"},{"horizon":3,"residual":37.2,"target_period":"2024-09-06"},{"horizon":3,"residual":32.6,"target_period":"2024-09-13"},{"horizon":3,"residual":54.6,"target_period":"2024-09-20"},{"horizon":3,"residual":-84,"target_period":"2024-09-27"},{"horizon":3,"residual":18.4,"target_period":"2024-10-04"},{"horizon":3,"residual":102.6,"target_period":"2024-10-11"},{"horizon":3,"residual":57,"target_period":"2024-10-18"},{"horizon":3,"residual":10.4,"target_period":"2024-10-25"},{"horizon":3,"residual":-35.4,"target_period":"2024-11-01"},{"horizon":3,"residual":-17.8,"target_period":"2024-11-08"},{"horizon":3,"residual":26.2,"target_period":"2024-11-15"},{"horizon":3,"residual":-88.6,"target_period":"2024-11-22"},{"horizon":3,"residual":154,"target_period":"2024-11-29"},{"horizon":3,"residual":-28.4,"target_period":"2024-12-06"},{"horizon":3,"residual":15.4,"target_period":"2024-12-13"},{"horizon":3,"residual":-66.8,"target_period":"2024-12-20"},{"horizon":3,"residual":-2,"target_period":"2024-12-27"},{"horizon":3,"residual":4.6,"target_period":"2025-01-03"},{"horizon":3,"residual":0.6,"target_period":"2025-01-10"},{"horizon":3,"residual":8.8,"target_period":"2025-01-17"},{"horizon":3,"residual":-76.6,"target_period":"2025-01-24"},{"horizon":3,"residual":-9,"target_period":"2025-01-31"},{"horizon":3,"residual":-116.6,"target_period":"2025-02-07"},{"horizon":3,"residual":-13.6,"target_period":"2025-02-14"},{"horizon":3,"residual":-97.6,"target_period":"2025-02-21"},{"horizon":3,"residual":-35.2,"target_period":"2025-02-28"},{"horizon":3,"residual":-66.2,"target_period":"2025-03-07"},{"horizon":3,"residual":-32.8,"target_period":"2025-03-14"},{"horizon":3,"residual":20,"target_period":"2025-03-21"},{"horizon":3,"residual":138.8,"target_period":"2025-03-28"},{"horizon":3,"residual":67.6,"target_period":"2025-04-04"},{"horizon":3,"residual":-51.4,"target_period":"2025-04-11"},{"horizon":3,"residual":0.4,"target_period":"2025-04-18"},{"horizon":3,"residual":-54,"target_period":"2025-04-25"},{"horizon":3,"residual":-47.6,"target_period":"2025-05-02"},{"horizon":3,"residual":56.6,"target_period":"2025-05-09"},{"horizon":3,"residual":9.4,"target_period":"2025-05-16"},{"horizon":3,"residual":-33.8,"target_period":"2025-05-23"},{"horizon":3,"residual":-16.2,"target_period":"2025-05-30"},{"horizon":3,"residual":10,"target_period":"2025-06-06"},{"horizon":3,"residual":-16.4,"target_period":"2025-06-13"},{"horizon":3,"residual":89,"target_period":"2025-06-20"},{"horizon":3,"residual":-36,"target_period":"2025-06-27"},{"horizon":3,"residual":28.4,"target_period":"2025-07-04"},{"horizon":3,"residual":8.4,"target_period":"2025-07-11"},{"horizon":3,"residual":65.4,"target_period":"2025-07-18"},{"horizon":3,"residual":-45.2,"target_period":"2025-07-25"},{"horizon":3,"residual":-93.6,"target_period":"2025-08-01"},{"horizon":3,"residual":51,"target_period":"2025-08-08"},{"horizon":3,"residual":14.6,"target_period":"2025-08-15"},{"horizon":3,"residual":-81.6,"target_period":"2025-08-22"},{"horizon":3,"residual":82.2,"target_period":"2025-08-29"},{"horizon":3,"residual":-0.2,"target_period":"2025-09-05"},{"horizon":3,"residual":-29.8,"target_period":"2025-09-12"},{"horizon":3,"residual":122.2,"target_period":"2025-09-19"},{"horizon":3,"residual":17,"target_period":"2025-09-26"},{"horizon":3,"residual":-22.6,"target_period":"2025-10-03"},{"horizon":3,"residual":-71.2,"target_period":"2025-10-10"},{"horizon":3,"residual":2.6,"target_period":"2025-10-17"},{"horizon":3,"residual":-87.4,"target_period":"2025-10-24"},{"horizon":3,"residual":-41,"target_period":"2025-10-31"},{"horizon":3,"residual":-70.4,"target_period":"2025-11-07"},{"horizon":3,"residual":80.4,"target_period":"2025-11-14"},{"horizon":3,"residual":85.8,"target_period":"2025-11-21"},{"horizon":3,"residual":-117,"target_period":"2025-11-28"},{"horizon":3,"residual":66.6,"target_period":"2025-12-05"},{"horizon":3,"residual":2.2,"target_period":"2025-12-12"},{"horizon":3,"residual":49.4,"target_period":"2025-12-19"},{"horizon":3,"residual":-13.4,"target_period":"2025-12-26"},{"horizon":3,"residual":147.8,"target_period":"2026-01-02"},{"horizon":3,"residual":52.4,"target_period":"2026-01-09"},{"horizon":3,"residual":107.2,"target_period":"2026-01-16"}],"usage":"additive_component_alignment_only"},"backtest":{"bias":91.1653333333,"by_horizon":[{"bias":90.0769230769,"directional_accuracy":0.5769230769,"forecast_errors":26,"horizon":1,"interval_coverage":{"80":0.4615384615,"90":0.6153846154,"95":0.7307692308},"mae":97.6307692308,"rmse":115.2176535619},{"bias":91.184,"directional_accuracy":0.64,"forecast_errors":25,"horizon":2,"interval_coverage":{"80":0.44,"90":0.6,"95":0.72},"mae":98.992,"rmse":116.8795756324},{"bias":92.325,"directional_accuracy":0.625,"forecast_errors":24,"horizon":3,"interval_coverage":{"80":0.4166666667,"90":0.5833333333,"95":0.7083333333},"mae":100.5083333333,"rmse":118.5243645838}],"directional_accuracy":0.6133333333,"evaluation_mode":"latest_revised_pseudo_out_of_sample","evaluation_window":{"end":"2026-07-17","start":"2026-01-23"},"forecast_errors":75,"interval_coverage":{"80":0.44,"90":0.6,"95":0.72},"mae":99.0053333333,"rmse":116.8375670179,"seasonal_naive_mae":94.88,"skill_vs_seasonal_naive":-0.0434794829,"status":"independent_holdout"},"dimensions":{"process":"EEX","product":"EPJK"},"forecast_kind":"univariate_statistical_projection","frequency":"weekly","generated_at":"2026-07-22T20:21:49.107490+00:00","geography_id":"us","horizon":{"periods":3,"unit":"weekly"},"limitations":["Uses latest stored provider values, not reconstructed first-release vintages.","Intervals are empirical rolling-origin error quantiles; nominal coverage is not guaranteed.","Univariate baseline excludes weather, outages, prices, analyst expectations, and other external features.","A methodology break or long missing-data gap can make the forecast unavailable."],"methodology_version":"2026-07-20.4","model":{"candidates":[{"forecast_errors":153,"label":"Seasonal average","mae":42.922875817,"model_id":"seasonal_average"},{"forecast_errors":153,"label":"Recent mean","mae":43.2850678733,"model_id":"recent_mean"},{"forecast_errors":153,"label":"Last observation","mae":44.8104575163,"model_id":"last_value"},{"forecast_errors":153,"label":"Robust damped trend","mae":47.7128660131,"model_id":"damped_trend"},{"forecast_errors":153,"label":"Additive harmonic trend","mae":52.5274274557,"model_id":"harmonic_trend"},{"forecast_errors":153,"label":"Seasonal naive","mae":62.5424836601,"model_id":"seasonal_naive"}],"label":"Seasonal average","model_id":"seasonal_average","selection_method":"rolling_origin_minimum_mae","selection_window":{"end":"2024-01-19","start":"2023-01-27"}},"origin":{"data_vintage_id":"da2f8f8fe8b1746caf4efe722de549152c83404ce878092ca78604844e33eb62","generated_at":"2026-07-22T20:21:49.107490+00:00","information_cutoff":"2026-07-22T20:21:49.107490+00:00","period":"2026-07-17","training_end":"2026-07-17","training_observations":655,"training_start":"2014-01-03","value":290,"vintage_policy":"latest_stored_provider_values_at_generation_time"},"points":[{"calibration_errors":104,"horizon":1,"intervals":{"80":{"lower":137.04,"upper":289.66},"90":{"lower":121.11,"upper":314.51},"95":{"lower":112.7,"upper":341.28}},"slot":30,"target_period":"2026-07-24","value":208,"year":2026},{"calibration_errors":103,"horizon":2,"intervals":{"80":{"lower":186.16,"upper":339.04},"90":{"lower":170.14,"upper":363.94},"95":{"lower":161.8,"upper":390.72}},"slot":31,"target_period":"2026-07-31","value":257,"year":2026},{"calibration_errors":102,"horizon":3,"intervals":{"80":{"lower":173.88,"upper":327.02},"90":{"lower":157.77,"upper":351.97},"95":{"lower":149.5,"upper":378.76}},"slot":32,"target_period":"2026-08-07","value":245,"year":2026}],"prediction_intervals":{"calibration_errors":309,"calibration_window":{"end":"2026-01-16","start":"2024-01-26"},"coverage_guarantee":false,"levels":[80,90,95],"method":"empirical_rolling_origin_residual_quantiles","minimum_errors_per_horizon":102},"schema_version":"1.0.0","status":"ok","target_series_id":"usa.eia.refined.jet.kerosene_type.exports.weekly","target_view_id":"usa.eia.refined.jet.kerosene_type.exports.weekly","training_source_checksum":"da2f8f8fe8b1746caf4efe722de549152c83404ce878092ca78604844e33eb62","unit":"thousand_barrels_per_day"}
