{"aggregation_residuals":{"alignment_keys":["horizon","target_period"],"calibration_window":{"end":"2025-04","start":"2021-10"},"centered_on":"published_calibrated_point","method":"rolling_origin_actual_minus_calibrated_point","minimum_aligned_samples_per_horizon":40,"sample_count":126,"samples":[{"horizon":1,"residual":54483,"target_period":"2021-10"},{"horizon":1,"residual":-1832.1666666667,"target_period":"2021-11"},{"horizon":1,"residual":-29810.1666666667,"target_period":"2021-12"},{"horizon":1,"residual":-9920.8333333335,"target_period":"2022-01"},{"horizon":1,"residual":-16921.1666666667,"target_period":"2022-02"},{"horizon":1,"residual":-37346.6666666667,"target_period":"2022-03"},{"horizon":1,"residual":-15236.6666666667,"target_period":"2022-04"},{"horizon":1,"residual":16252.1666666665,"target_period":"2022-05"},{"horizon":1,"residual":-22232.3333333335,"target_period":"2022-06"},{"horizon":1,"residual":-26814,"target_period":"2022-07"},{"horizon":1,"residual":17452.1666666665,"target_period":"2022-08"},{"horizon":1,"residual":-11414.8333333335,"target_period":"2022-09"},{"horizon":1,"residual":-10692.6666666667,"target_period":"2022-10"},{"horizon":1,"residual":18469,"target_period":"2022-11"},{"horizon":1,"residual":32339.3333333333,"target_period":"2022-12"},{"horizon":1,"residual":20877.3333333333,"target_period":"2023-01"},{"horizon":1,"residual":9134.6666666665,"target_period":"2023-02"},{"horizon":1,"residual":45919.3333333333,"target_period":"2023-03"},{"horizon":1,"residual":91270.6666666665,"target_period":"2023-04"},{"horizon":1,"residual":34367.6666666665,"target_period":"2023-05"},{"horizon":1,"residual":-7647.6666666667,"target_period":"2023-06"},{"horizon":1,"residual":12588.8333333333,"target_period":"2023-07"},{"horizon":1,"residual":4989.5,"target_period":"2023-08"},{"horizon":1,"residual":28782.5,"target_period":"2023-09"},{"horizon":1,"residual":84974,"target_period":"2023-10"},{"horizon":1,"residual":28632.6666666665,"target_period":"2023-11"},{"horizon":1,"residual":7588.3333333333,"target_period":"2023-12"},{"horizon":1,"residual":-29349.5,"target_period":"2024-01"},{"horizon":1,"residual":-7384.6666666667,"target_period":"2024-02"},{"horizon":1,"residual":0,"target_period":"2024-03"},{"horizon":1,"residual":130872.1666666665,"target_period":"2024-04"},{"horizon":1,"residual":36226,"target_period":"2024-05"},{"horizon":1,"residual":-61858.1666666667,"target_period":"2024-06"},{"horizon":1,"residual":-7536.3333333335,"target_period":"2024-07"},{"horizon":1,"residual":25841.8333333333,"target_period":"2024-08"},{"horizon":1,"residual":-49108,"target_period":"2024-09"},{"horizon":1,"residual":-116244.1666666667,"target_period":"2024-10"},{"horizon":1,"residual":-17753.3333333335,"target_period":"2024-11"},{"horizon":1,"residual":90783.8333333333,"target_period":"2024-12"},{"horizon":1,"residual":113663.3333333333,"target_period":"2025-01"},{"horizon":1,"residual":-18000.8333333335,"target_period":"2025-02"},{"horizon":1,"residual":-6051.8333333335,"target_period":"2025-03"},{"horizon":1,"residual":-27416.5,"target_period":"2025-04"},{"horizon":2,"residual":49.8333333335,"target_period":"2021-11"},{"horizon":2,"residual":-33076.3333333335,"target_period":"2021-12"},{"horizon":2,"residual":-19967.3333333335,"target_period":"2022-01"},{"horizon":2,"residual":-22633,"target_period":"2022-02"},{"horizon":2,"residual":-41431.3333333335,"target_period":"2022-03"},{"horizon":2,"residual":-22101.8333333335,"target_period":"2022-04"},{"horizon":2,"residual":-49.8333333335,"target_period":"2022-05"},{"horizon":2,"residual":-26931,"target_period":"2022-06"},{"horizon":2,"residual":-33502.5,"target_period":"2022-07"},{"horizon":2,"residual":7244.8333333335,"target_period":"2022-08"},{"horizon":2,"residual":-13827,"target_period":"2022-09"},{"horizon":2,"residual":-14233,"target_period":"2022-10"},{"horizon":2,"residual":11918.1666666665,"target_period":"2022-11"},{"horizon":2,"residual":27025.8333333335,"target_period":"2022-12"},{"horizon":2,"residual":24187.1666666665,"target_period":"2023-01"},{"horizon":2,"residual":12964.1666666665,"target_period":"2023-02"},{"horizon":2,"residual":42753.5,"target_period":"2023-03"},{"horizon":2,"residual":98921.1666666665,"target_period":"2023-04"},{"horizon":2,"residual":51321.5,"target_period":"2023-05"},{"horizon":2,"residual":-1120.5,"target_period":"2023-06"},{"horizon":2,"residual":11775.1666666665,"target_period":"2023-07"},{"horizon":2,"residual":8771.6666666665,"target_period":"2023-08"},{"horizon":2,"residual":33247.3333333335,"target_period":"2023-09"},{"horizon":2,"residual":88545.3333333335,"target_period":"2023-10"},{"horizon":2,"residual":33330.8333333335,"target_period":"2023-11"},{"horizon":2,"residual":10337.5,"target_period":"2023-12"},{"horizon":2,"residual":-23734.8333333335,"target_period":"2024-01"},{"horizon":2,"residual":-10227.6666666665,"target_period":"2024-02"},{"horizon":2,"residual":980.1666666665,"target_period":"2024-03"},{"horizon":2,"residual":128536.8333333335,"target_period":"2024-04"},{"horizon":2,"residual":45353,"target_period":"2024-05"},{"horizon":2,"residual":-58377.1666666665,"target_period":"2024-06"},{"horizon":2,"residual":-16773.3333333335,"target_period":"2024-07"},{"horizon":2,"residual":29339.5,"target_period":"2024-08"},{"horizon":2,"residual":-42651.3333333335,"target_period":"2024-09"},{"horizon":2,"residual":-122597.1666666665,"target_period":"2024-10"},{"horizon":2,"residual":-57777.3333333335,"target_period":"2024-11"},{"horizon":2,"residual":74757.5,"target_period":"2024-12"},{"horizon":2,"residual":128822.6666666665,"target_period":"2025-01"},{"horizon":2,"residual":-4015.8333333335,"target_period":"2025-02"},{"horizon":2,"residual":-17826,"target_period":"2025-03"},{"horizon":2,"residual":-27746,"target_period":"2025-04"},{"horizon":3,"residual":-31750.6666666665,"target_period":"2021-12"},{"horizon":3,"residual":-23789.8333333333,"target_period":"2022-01"},{"horizon":3,"residual":-33235.8333333333,"target_period":"2022-02"},{"horizon":3,"residual":-47699.5,"target_period":"2022-03"},{"horizon":3,"residual":-26742.8333333333,"target_period":"2022-04"},{"horizon":3,"residual":-7471.3333333333,"target_period":"2022-05"},{"horizon":3,"residual":-43789.3333333333,"target_period":"2022-06"},{"horizon":3,"residual":-38757.5,"target_period":"2022-07"},{"horizon":3,"residual":0,"target_period":"2022-08"},{"horizon":3,"residual":-24590.6666666665,"target_period":"2022-09"},{"horizon":3,"residual":-17201.5,"target_period":"2022-10"},{"horizon":3,"residual":7821.5,"target_period":"2022-11"},{"horizon":3,"residual":19918.6666666667,"target_period":"2022-12"},{"horizon":3,"residual":18317.3333333335,"target_period":"2023-01"},{"horizon":3,"residual":15717.6666666667,"target_period":"2023-02"},{"horizon":3,"residual":46026.6666666667,"target_period":"2023-03"},{"horizon":3,"residual":95199,"target_period":"2023-04"},{"horizon":3,"residual":58415.6666666667,"target_period":"2023-05"},{"horizon":3,"residual":15277,"target_period":"2023-06"},{"horizon":3,"residual":17746,"target_period":"2023-07"},{"horizon":3,"residual":7401.6666666667,"target_period":"2023-08"},{"horizon":3,"residual":36473.1666666667,"target_period":"2023-09"},{"horizon":3,"residual":92453.8333333335,"target_period":"2023-10"},{"horizon":3,"residual":36345.8333333335,"target_period":"2023-11"},{"horizon":3,"residual":14479.3333333335,"target_period":"2023-12"},{"horizon":3,"residual":-21542,"target_period":"2024-01"},{"horizon":3,"residual":-5169.3333333333,"target_period":"2024-02"},{"horizon":3,"residual":-2419.1666666665,"target_period":"2024-03"},{"horizon":3,"residual":128960.6666666667,"target_period":"2024-04"},{"horizon":3,"residual":42461.3333333335,"target_period":"2024-05"},{"horizon":3,"residual":-49806.5,"target_period":"2024-06"},{"horizon":3,"residual":-13848.6666666665,"target_period":"2024-07"},{"horizon":3,"residual":19546.1666666667,"target_period":"2024-08"},{"horizon":3,"residual":-39710,"target_period":"2024-09"},{"horizon":3,"residual":-116696.8333333333,"target_period":"2024-10"},{"horizon":3,"residual":-64686.6666666665,"target_period":"2024-11"},{"horizon":3,"residual":34177.1666666667,"target_period":"2024-12"},{"horizon":3,"residual":112240,"target_period":"2025-01"},{"horizon":3,"residual":10587.1666666667,"target_period":"2025-02"},{"horizon":3,"residual":-4397.3333333333,"target_period":"2025-03"},{"horizon":3,"residual":-40076.5,"target_period":"2025-04"}],"usage":"additive_component_alignment_only"},"backtest":{"bias":19813.4646464646,"by_horizon":[{"bias":18002.4444444444,"directional_accuracy":0.75,"forecast_errors":12,"horizon":1,"interval_coverage":{"80":0.6666666667,"90":0.75,"95":0.9166666667},"mae":46302,"rmse":55204.3184942688},{"bias":17680.7121212121,"directional_accuracy":0.7272727273,"forecast_errors":11,"horizon":2,"interval_coverage":{"80":0.8181818182,"90":0.9090909091,"95":1},"mae":52650.0151515152,"rmse":58372.104534749},{"bias":24332.7166666667,"directional_accuracy":0.9,"forecast_errors":10,"horizon":3,"interval_coverage":{"80":0.7,"90":0.9,"95":0.9},"mae":50411.1166666667,"rmse":59518.8685837198}],"directional_accuracy":0.7878787879,"evaluation_mode":"latest_revised_pseudo_out_of_sample","evaluation_window":{"end":"2026-04","start":"2025-05"},"forecast_errors":33,"interval_coverage":{"80":0.7272727273,"90":0.8484848485,"95":0.9393939394},"mae":49663.1919191919,"rmse":57597.2134757991,"seasonal_naive_mae":58366.7575757576,"skill_vs_seasonal_naive":0.1491185397,"status":"independent_holdout"},"dimensions":{"coordinate":"8.34.1","vector":"v107757626"},"forecast_kind":"univariate_statistical_projection","frequency":"monthly","generated_at":"2026-07-20T19:20:43.789785+00:00","geography_id":"ca.mb","horizon":{"periods":3,"unit":"monthly"},"limitations":["Uses latest stored provider values, not reconstructed first-release vintages.","Intervals are empirical rolling-origin error quantiles; nominal coverage is not guaranteed.","Univariate baseline excludes weather, outages, prices, analyst expectations, and other external features.","A methodology break or long missing-data gap can make the forecast unavailable."],"methodology_version":"2026-07-20.4","model":{"candidates":[{"forecast_errors":24,"label":"Recent mean","mae":21231.7222222222,"model_id":"recent_mean"},{"forecast_errors":24,"label":"Additive harmonic trend","mae":21301.5876453511,"model_id":"harmonic_trend"},{"forecast_errors":24,"label":"Last observation","mae":22963.3333333333,"model_id":"last_value"},{"forecast_errors":24,"label":"Seasonal average","mae":24641.8333333333,"model_id":"seasonal_average"},{"forecast_errors":24,"label":"Seasonal naive","mae":25779.25,"model_id":"seasonal_naive"},{"forecast_errors":24,"label":"Robust damped trend","mae":26032.416484375,"model_id":"damped_trend"}],"label":"Recent mean","model_id":"recent_mean","selection_method":"rolling_origin_minimum_mae","selection_window":{"end":"2021-09","start":"2021-01"}},"origin":{"data_vintage_id":"140cb5743fa2148b314ffe1a783e60cd6ee879d9b34479d4ee57b56a87a3d61c","generated_at":"2026-07-20T19:20:43.789785+00:00","information_cutoff":"2026-07-20T19:20:43.789785+00:00","period":"2026-04","training_end":"2026-04","training_observations":88,"training_start":"2019-01","value":1694309,"vintage_policy":"latest_stored_provider_values_at_generation_time"},"points":[{"calibration_errors":43,"horizon":1,"intervals":{"80":{"lower":1610656.1333333333,"upper":1719249.9666666668},"90":{"lower":1592442.3,"upper":1731596.15},"95":{"lower":1579153.5083333333,"upper":1752917.8666666665}},"slot":5,"target_period":"2026-05","value":1640374.1666666667,"year":2026},{"calibration_errors":42,"horizon":2,"intervals":{"80":{"lower":1601222.8833333333,"upper":1714275.2333333332},"90":{"lower":1584840.3,"upper":1740263.7083333333},"95":{"lower":1583499.1625,"upper":1769657.7750000001}},"slot":6,"target_period":"2026-06","value":1641861.3333333335,"year":2026},{"calibration_errors":41,"horizon":3,"intervals":{"80":{"lower":1600115.5,"upper":1702320.5},"90":{"lower":1594098.3333333333,"upper":1739103.8333333333},"95":{"lower":1579218.1666666667,"upper":1756144.8333333333}},"slot":7,"target_period":"2026-07","value":1643904.8333333333,"year":2026}],"prediction_intervals":{"calibration_errors":126,"calibration_window":{"end":"2025-04","start":"2021-10"},"coverage_guarantee":false,"levels":[80,90,95],"method":"empirical_rolling_origin_residual_quantiles","minimum_errors_per_horizon":41},"schema_version":"1.0.0","status":"ok","target_series_id":"can.statcan.crude.closing_inventory.monthly","target_view_id":"can.statcan.crude.closing_inventory.monthly","training_source_checksum":"140cb5743fa2148b314ffe1a783e60cd6ee879d9b34479d4ee57b56a87a3d61c","unit":"cubic_metres"}
